as_op_doubleweave/__init__.py
as_op_doubleweave/as_op_doubleweave.py
as_op_doubleweave/entry_points.py
as_op_doubleweave/expected_error.py
as_op_doubleweave/filter_pattern.py
as_op_doubleweave/read_pattern.py
as_op_doubleweave/version.py
as_op_doubleweave-0.30.dist-info/LICENSE.txt
as_op_doubleweave-0.30.dist-info/METADATA
as_op_doubleweave-0.30.dist-info/WHEEL
as_op_doubleweave-0.30.dist-info/entry_points.txt
as_op_doubleweave-0.30.dist-info/top_level.txt
as_op_doubleweave-0.30.dist-info/RECORD
