Metadata-Version: 2.1
Name: as_op_doubleweave
Version: 0.30
Summary: Convert weaving patterns to overshot-patterned double weave
Author-email: Russell Owen <r3owen@gmail.com>
Project-URL: Homepage, https://github.com/r-owen/as_op_doubleweave
Project-URL: Issues, https://github.com/r-owen/as_op_doubleweave/issues
Classifier: Programming Language :: Python :: 3
Classifier: License :: OSI Approved :: MIT License
Classifier: Operating System :: OS Independent
Requires-Python: >=3.11
License-File: LICENSE.txt
Requires-Dist: dtx_to_wif>=3.0
Provides-Extra: dev
Requires-Dist: pre-commit>=3.8; extra == "dev"
Requires-Dist: pytest>=8.3; extra == "dev"
